yt_cc_dl/__init__.py
yt_cc_dl/cli.py
yt_cc_dl/downloader.py
yt_cc_dl-0.1.5.dist-info/LICENSE
yt_cc_dl-0.1.5.dist-info/METADATA
yt_cc_dl-0.1.5.dist-info/WHEEL
yt_cc_dl-0.1.5.dist-info/entry_points.txt
yt_cc_dl-0.1.5.dist-info/RECORD
