Metadata-Version: 2.1
Name: yt-cc-dl
Version: 0.1.5
Summary: Command-line program to download closed captions (subtitles) of videos from YouTube.com
License: MIT
Author: Alyetama
Author-email: malyetama@pm.me
Requires-Python: >=3.7,<4.0
Classifier: License :: OSI Approved :: MIT License
Classifier: Programming Language :: Python :: 3
Classifier: Programming Language :: Python :: 3.7
Classifier: Programming Language :: Python :: 3.8
Classifier: Programming Language :: Python :: 3.9
Classifier: Programming Language :: Python :: 3.10
Classifier: Programming Language :: Python :: 3.11
Classifier: Programming Language :: Python :: 3.12
Requires-Dist: loguru (>=0.6.0)
Requires-Dist: requests (>=2.2)
Requires-Dist: requests-toolbelt (>=1.0.0)
Requires-Dist: tqdm (>=4.0)
Requires-Dist: yt-dlp
